{
  "$schema": "https://nitro.margelo.com/nitro.schema.json",
  "cxxNamespace": ["nitroreadium"],
  "ios": {
    "iosModuleName": "NitroReadium"
  },
  "android": {
    "androidNamespace": ["nitroreadium"],
    "androidCxxLibName": "NitroReadium"
  },
  "autolinking": {
    "NitroReadium": {
      "swift": "HybridNitroReadium",
      "kotlin": "HybridNitroReadium"
    },
    "ReadiumModule": {
      "swift": "HybridReadiumModule",
      "kotlin": "HybridReadiumModule"
    }
  },
  "ignorePaths": ["**/node_modules"]
}

